twitter_plugin_gamesdk/game_twitter_auth.py
twitter_plugin_gamesdk/twitter_plugin.py
twitter_plugin_gamesdk-0.2.11.dist-info/METADATA
twitter_plugin_gamesdk-0.2.11.dist-info/WHEEL
twitter_plugin_gamesdk-0.2.11.dist-info/entry_points.txt
twitter_plugin_gamesdk-0.2.11.dist-info/RECORD
