Metadata-Version: 2.3
Name: twitter-plugin-gamesdk
Version: 0.2.11
Summary: Twitter Plugin for Python SDK for GAME by Virtuals
Author: Celeste Ang
Author-email: celeste@virtuals.io
Requires-Python: >=3.9
Classifier: Programming Language :: Python :: 3
Classifier: Programming Language :: Python :: 3.9
Classifier: Programming Language :: Python :: 3.10
Classifier: Programming Language :: Python :: 3.11
Classifier: Programming Language :: Python :: 3.12
Classifier: Programming Language :: Python :: 3.13
Requires-Dist: tweepy (>=4.15.0)
Requires-Dist: virtuals-tweepy (>=0.1.5)
Project-URL: Homepage, https://github.com/game-by-virtuals/game-python
Project-URL: Repository, https://github.com/game-by-virtuals/game-python
